respond_model/__init__.py
respond_model/apps.py
respond_model/choices.py
respond_model/constants.py
respond_model/diagnoses.py
respond_model/stubs.py
respond_model/form_validators/__init__.py
respond_model/form_validators/bp_form_validator_mixin.py
respond_model/form_validators/crf_form_validator_mixin.py
respond_model/form_validators/diagnosis_form_validator_mixin.py
respond_model/form_validators/drug_refill_form_validator_mixin.py
respond_model/form_validators/glucose_form_validator_mixin.py
respond_model/form_validators/hiv_initial_review_form_validator.py
respond_model/form_validators/initial_review_form_validator_mixin.py
respond_model/form_validators/medication_adherence_form_validator_mixin.py
respond_model/form_validators/result_form_validator_mixin.py
respond_model/form_validators/review_form_validator_mixin.py
respond_model/model_mixins/__init__.py
respond_model/model_mixins/creatinine_fields_model_mixin.py
respond_model/model_mixins/drug_refill_model_mixin.py
respond_model/model_mixins/drug_supply_model_mixin.py
respond_model/model_mixins/fasting_glucose_model_mixin.py
respond_model/model_mixins/fasting_model_mixin.py
respond_model/model_mixins/glucose_model_mixin.py
respond_model/model_mixins/medication_adherence_model_mixin.py
respond_model/model_mixins/ogtt_model_mixin.py
respond_model/model_mixins/phq9_model_mixin.py
respond_model/model_mixins/review_model_mixin.py
respond_model/model_mixins/blood_results/__init__.py
respond_model/model_mixins/blood_results/blood_result_fbc_model_mixin.py
respond_model/model_mixins/blood_results/blood_results_lipid_model_mixin.py
respond_model/model_mixins/clinical_review/__init__.py
respond_model/model_mixins/clinical_review/clinical_review.py
respond_model/model_mixins/clinical_review/clinical_review_baseline.py
respond_model/model_mixins/complications_model_mixin/__init__.py
respond_model/model_mixins/complications_model_mixin/complications_baseline_model_mixin.py
respond_model-0.1.3.dist-info/LICENSE
respond_model-0.1.3.dist-info/METADATA
respond_model-0.1.3.dist-info/WHEEL
respond_model-0.1.3.dist-info/top_level.txt
respond_model-0.1.3.dist-info/RECORD
